trajectorytools/__init__.py
trajectorytools/collective.py
trajectorytools/constants.py
trajectorytools/geometry.py
trajectorytools/interpolate.py
trajectorytools/trajectories.py
trajectorytools/animation/__init__.py
trajectorytools/animation/animation.py
trajectorytools/animation/plotter.py
trajectorytools/animation/scatter.py
trajectorytools/data/test_trajectories.npy
trajectorytools/data/test_trajectories_idtrackerai.npy
trajectorytools/data/test_trajectories_idtrackerai_with_border.npy
trajectorytools/data/trajectories_with_points.npy
trajectorytools/examples/animate.py
trajectorytools/examples/animate_border.py
trajectorytools/examples/bouts_analysis.py
trajectorytools/examples/example.py
trajectorytools/examples/follow_animate.py
trajectorytools/fish_bouts/__init__.py
trajectorytools/fish_bouts/fish_bouts.py
trajectorytools/plot/__init__.py
trajectorytools/plot/plot.py
trajectorytools/plot/polar.py
trajectorytools/socialcontext/__init__.py
trajectorytools/socialcontext/leadership.py
trajectorytools/socialcontext/socialcontext.py
trajectorytools-0.4.2.dist-info/licenses/COPYING
trajectorytools-0.4.2.dist-info/METADATA
trajectorytools-0.4.2.dist-info/WHEEL
trajectorytools-0.4.2.dist-info/top_level.txt
trajectorytools-0.4.2.dist-info/RECORD
