Metadata-Version: 2.4
Name: trajectorytools
Version: 0.4.2
Summary: A tool to study 2D trajectories
Author: Jordi Torrents, Dean Rance, Francisco Romero Ferrero, Francisco J.H. Heras, Gonzalo Polavieja
Project-URL: Repository, https://gitlab.com/polavieja_lab/trajectorytools
Classifier: License :: OSI Approved :: GNU General Public License v3 (GPLv3)
Classifier: Programming Language :: Python
Classifier: Topic :: Scientific/Engineering
Classifier: Topic :: Scientific/Engineering :: Physics
Classifier: Topic :: Software Development :: Libraries
Classifier: Topic :: Utilities
Requires-Python: >=3.10
License-File: COPYING
Requires-Dist: scipy
Requires-Dist: scikit-learn
Requires-Dist: matplotlib
Requires-Dist: h5py
Requires-Dist: miniballcpp
Dynamic: license-file
